signe/__init__.py
signe/core/__init__.py
signe/core/async_computed.py
signe/core/batch.py
signe/core/cleanup.py
signe/core/collections.py
signe/core/computed.py
signe/core/consts.py
signe/core/context.py
signe/core/deps.py
signe/core/effect.py
signe/core/helper.py
signe/core/id_generator.py
signe/core/mixins.py
signe/core/on.py
signe/core/protocols.py
signe/core/reactive.py
signe/core/runtime.py
signe/core/scope.py
signe/core/signal.py
signe/core/types.py
signe/version.py
signe-0.4.23.dist-info/LICENSE
signe-0.4.23.dist-info/METADATA
signe-0.4.23.dist-info/WHEEL
signe-0.4.23.dist-info/RECORD
