Metadata-Version: 2.1
Name: signe
Version: 0.4.23
Summary: A responsive system implemented in python with reference to the core mechanisms of S.js and vue reactivity.
Home-page: https://github.com/CrystalWindSnake/py-signe
License: MIT
Keywords: python,reactivity,reactivity-system
Author: CrystalWindSnake
Author-email: 568166495@qq.com
Requires-Python: >=3.8,<4.0
Classifier: License :: OSI Approved :: MIT License
Classifier: Programming Language :: Python :: 3
Classifier: Programming Language :: Python :: 3.8
Classifier: Programming Language :: Python :: 3.9
Classifier: Programming Language :: Python :: 3.10
Classifier: Programming Language :: Python :: 3.11
Classifier: Programming Language :: Python :: 3.12
Requires-Dist: typing-extensions (>=4.0.0)
Project-URL: Repository, https://github.com/CrystalWindSnake/py-signe
